definitions.py
icon/__init__.py
icon/cli.py
icon/commands/__init__.py
icon/commands/appicon.py
icon/commands/helpers.py
icon/commands/tabbar.py
icon_resizer-0.0.3.data/data/LICENSE.txt
icon_resizer-0.0.3.data/data/README.md
icon_resizer-0.0.3.dist-info/DESCRIPTION.rst
icon_resizer-0.0.3.dist-info/METADATA
icon_resizer-0.0.3.dist-info/RECORD
icon_resizer-0.0.3.dist-info/WHEEL
icon_resizer-0.0.3.dist-info/entry_points.txt
icon_resizer-0.0.3.dist-info/metadata.json
icon_resizer-0.0.3.dist-info/top_level.txt
